{"title":"노들섬 ─ 프로그램 ─ 전체 ─ 전시","url":"https://nodeul.org/types/exhibit/","favicon":"https://s3-ap-northeast-2.amazonaws.com/nodeul-denomix/wp-content/themes/nodeul/img/favicons/favicon-32x32.png?v=190814","elements":[{"title":"2023 서울드럼페스티벌","contents":"2023.05.26 (금) 17:00","link":"https://nodeul.org/program/2023-%ec%84%9c%ec%9a%b8%eb%93%9c%eb%9f%bc%ed%8e%98%ec%8a%a4%ed%8b%b0%eb%b2%8c/","retrieved":1684258815736,"image":"https://d27rhg3fr98tz.cloudfront.net/wp-content/uploads/2023/05/17054813/%ED%99%88%ED%8E%98%EC%9D%B4%EC%A7%80-%ED%8F%AC%EC%8A%A4%ED%84%B0-600X900-png-01-227x282.png"},{"title":"노들 글로벌 예술섬 디자인 공모 작품 전시","contents":"2023.05.23 (화)","link":"https://nodeul.org/program/%eb%85%b8%eb%93%a4-%ea%b8%80%eb%a1%9c%eb%b2%8c-%ec%98%88%ec%88%a0%ec%84%ac-%eb%94%94%ec%9e%90%ec%9d%b8-%ea%b3%b5%eb%aa%a8-%ec%9e%91%ed%92%88-%ec%a0%84%ec%8b%9c/","retrieved":1684431628332,"image":"https://d27rhg3fr98tz.cloudfront.net/wp-content/uploads/2023/05/19040046/%EB%85%B8%EB%93%A4%EC%98%88%EC%88%A0%EC%84%AC%ED%8F%AC%EC%8A%A4%ED%84%B0-227x282.jpg"},{"title":"2023 서울재즈페스타","contents":"2023.04.28 (금)","link":"https://nodeul.org/program/2023-%ec%84%9c%ec%9a%b8%ec%9e%ac%ec%a6%88%ed%8e%98%ec%8a%a4%ed%83%80/","retrieved":1681709974191,"image":"https://d27rhg3fr98tz.cloudfront.net/wp-content/uploads/2023/04/17200411/2023%EC%84%9C%EC%9A%B8%EC%9E%AC%EC%A6%88%ED%8E%98%EC%8A%A4%ED%83%80_%EB%85%B8%EB%93%A4%EC%84%AC_%ED%99%88%ED%8E%98%EC%9D%B4%EC%A7%80%ED%8F%AC%EC%8A%A4%ED%84%B0-227x282.jpg"},{"title":"에그박사팀의 연구실 in 노들섬","contents":"2023.03.01 (수) 11:00","link":"https://nodeul.org/program/15219-2/","retrieved":1677130839133,"image":"https://d27rhg3fr98tz.cloudfront.net/wp-content/uploads/2023/02/16005114/%ED%8F%AC%EC%8A%A4%ED%84%B0-100-227x282.jpg"},{"title":"2022 서울그린아트페스티벌_그린재즈무브먼트","contents":"2022.12.07 (수)","link":"https://nodeul.org/program/2022-%ec%84%9c%ec%9a%b8%ea%b7%b8%eb%a6%b0%ec%95%84%ed%8a%b8%ed%8e%98%ec%8a%a4%ed%8b%b0%eb%b2%8c_%ea%b7%b8%eb%a6%b0%ec%9e%ac%ec%a6%88%eb%ac%b4%eb%b8%8c%eb%a8%bc%ed%8a%b8/","retrieved":1677130839135,"image":"https://d27rhg3fr98tz.cloudfront.net/wp-content/uploads/2022/11/09194604/2022%EC%84%9C%EC%9A%B8%EA%B7%B8%EB%A6%B0%ED%8E%98%EC%8A%A4%ED%8B%B0%EB%B2%8C_%EB%85%B8%EB%93%A4%EC%84%AC_%ED%99%88%ED%8E%98%EC%9D%B4%EC%A7%80%ED%8F%AC%EC%8A%A4%ED%84%B0-227x282.jpg"},{"title":"2022 한국예술종합학교 무대미술과 졸업전시","contents":"2022.12.06 (화)","link":"https://nodeul.org/program/2022-%ed%95%9c%ea%b5%ad%ec%98%88%ec%88%a0%ec%a2%85%ed%95%a9%ed%95%99%ea%b5%90-%eb%ac%b4%eb%8c%80%eb%af%b8%ec%88%a0%ea%b3%bc-%ec%a1%b8%ec%97%85%ec%a0%84%ec%8b%9c/","retrieved":1677130839137,"image":"https://d27rhg3fr98tz.cloudfront.net/wp-content/uploads/2022/11/29234737/%EC%98%A8%EB%9D%BC%EC%9D%B8-%ED%99%8D%EB%B3%B4%EB%AC%BC-%ED%99%88%ED%8E%98%EC%9D%B4%EC%A7%80-%ED%8F%AC%EC%8A%A4%ED%84%B0_%EB%B3%80%ED%99%98-227x282.png"},{"title":"[지금은] 녹아내리는 중","contents":"2022.12.03 (토)","link":"https://nodeul.org/program/%ec%a7%80%ea%b8%88%ec%9d%80-%eb%85%b9%ec%95%84%eb%82%b4%eb%a6%ac%eb%8a%94-%ec%a4%91/","retrieved":1677130839138,"image":"https://d27rhg3fr98tz.cloudfront.net/wp-content/uploads/2022/11/30002712/%ED%8F%AC%EC%8A%A4%ED%84%B0-600x900.JPG-227x282.jpg"},{"title":"나는 죽은 자와 함께 걷는다","contents":"2022.11.26 (토)","link":"https://nodeul.org/program/%eb%82%98%eb%8a%94-%ec%a3%bd%ec%9d%80-%ec%9e%90%ec%99%80-%ed%95%a8%ea%bb%98-%ea%b1%b7%eb%8a%94%eb%8b%a4/","retrieved":1677130839146,"image":"https://d27rhg3fr98tz.cloudfront.net/wp-content/uploads/2022/11/23051820/zombie_homepage_600x900_150dpi-227x282.jpg"},{"title":"FFALO in SEOUL (팔로인서울)","contents":"2022.11.08 (화)","link":"https://nodeul.org/program/ffalo-in-seoul-%ed%8c%94%eb%a1%9c%ec%9d%b8%ec%84%9c%ec%9a%b8/","retrieved":1677130839147,"image":"https://d27rhg3fr98tz.cloudfront.net/wp-content/uploads/2022/11/05034644/%ED%99%88%ED%8E%98%EC%9D%B4%EC%A7%80%ED%8F%AC%EC%8A%A4%ED%84%B0-FFALOinSEOUL-600900-227x282.jpg"},{"title":"2022 제5회 대한민국패럴스마트폰영화제","contents":"2022.11.03 (목)","link":"https://nodeul.org/program/2022-%ec%a0%9c5%ed%9a%8c-%eb%8c%80%ed%95%9c%eb%af%bc%ea%b5%ad%ed%8c%a8%eb%9f%b4%ec%8a%a4%eb%a7%88%ed%8a%b8%ed%8f%b0%ec%98%81%ed%99%94%ec%a0%9c/","retrieved":1677130839148,"image":"https://d27rhg3fr98tz.cloudfront.net/wp-content/uploads/2022/10/03215801/%EC%98%A8%EB%9D%BC%EC%9D%B8%ED%99%8D%EB%B3%B4%EB%AC%BC_%ED%99%88%ED%8E%98%EC%9D%B4%EC%A7%80-%ED%8F%AC%EC%8A%A4%ED%84%B0_600x900px-227x282.jpg"},{"title":"SPACE NARRATIVE","contents":"2022.10.28 (금)","link":"https://nodeul.org/program/space-narrative/","retrieved":1677130839149,"image":"https://d27rhg3fr98tz.cloudfront.net/wp-content/uploads/2022/10/21224215/%ED%8F%AC%EC%8A%A4%ED%84%B0-%ED%81%AC%EA%B8%B0%EC%A1%B0%EC%A0%95-227x282.jpg"},{"title":"발자국 제 15회 전시 <다시 시작, 섬>","contents":"2022.10.15 (토)","link":"https://nodeul.org/program/%eb%b0%9c%ec%9e%90%ea%b5%ad-%ec%a0%9c-15%ed%9a%8c-%ec%a0%84%ec%8b%9c/","retrieved":1677130839150,"image":"https://d27rhg3fr98tz.cloudfront.net/wp-content/uploads/2022/10/04220349/789-227x282.jpg"}]}