{"title":"노들섬 ─ 프로그램 ─ 예정 ─ 공연","url":"https://nodeul.org/program-planned/#show","favicon":"https://s3-ap-northeast-2.amazonaws.com/nodeul-denomix/wp-content/themes/nodeul/img/favicons/favicon-32x32.png?v=190814","elements":[{"title":"럭키테이프스 내한공연 (LUCKY TAPES LIVE IN SEOUL)","contents":"2023.06.25 (일) 18:00","link":"https://nodeul.org/program/%eb%9f%ad%ed%82%a4%ed%85%8c%ec%9d%b4%ed%94%84%ec%8a%a4-%eb%82%b4%ed%95%9c%ea%b3%b5%ec%97%b0-lucky-tapes-live-in-seoul/","retrieved":1681191628544,"image":"https://d27rhg3fr98tz.cloudfront.net/wp-content/uploads/2023/04/11234008/LUCKYTAPES%EA%B3%B5%EC%97%B0-%EC%9B%B9%ED%8F%AC%EC%8A%A4%ED%84%B0-600x900px--227x282.jpg"},{"title":"터치드(TOUCHED) 콘서트 ‘SUPERNOVA’","contents":"2023.06.10 (토)","link":"https://nodeul.org/program/%ed%84%b0%ec%b9%98%eb%93%9ctouched-%ec%bd%98%ec%84%9c%ed%8a%b8-supernova/","retrieved":1683697235512,"image":"https://d27rhg3fr98tz.cloudfront.net/wp-content/uploads/2023/05/10222901/SUPERNOVA_%EB%85%B8%EB%93%A4%EC%84%AC%ED%99%88%ED%8E%98%EC%9D%B4%EC%A7%80_%ED%8F%AC%EC%8A%A4%ED%84%B0-227x282.jpg"},{"title":"Phum Viphurit Live in Seoul 2023","contents":"2023.05.21 (일) 17:00","link":"https://nodeul.org/program/phum-viphurit-live-in-seoul-2023/","retrieved":1683697235513,"image":"https://d27rhg3fr98tz.cloudfront.net/wp-content/uploads/2023/05/10212135/%ED%92%88%EB%B9%84%ED%91%B8%EB%A6%BF-%ED%8F%AC%EC%8A%A4%ED%84%B0-227x282.jpg"},{"title":"시티포레스티벌 2023","contents":"2023.05.20 (토)","link":"https://nodeul.org/program/%ec%8b%9c%ed%8b%b0%ed%8f%ac%eb%a0%88%ec%8a%a4%ed%8b%b0%eb%b2%8c-2023/","retrieved":1682487605565,"image":"https://d27rhg3fr98tz.cloudfront.net/wp-content/uploads/2023/04/26201756/%EC%8B%9C%ED%8F%AC%EB%A0%88_%EB%85%B8%EB%93%A4%EC%84%AC_%ED%8F%AC%EC%8A%A4%ED%84%B0-227x282.jpg"},{"title":"2023 원광대학교 45회 졸업 패션쇼 ‘TIME: CHRONOLOGY’","contents":"2023.05.19 (금)","link":"https://nodeul.org/program/2023-%ec%9b%90%ea%b4%91%eb%8c%80%ed%95%99%ea%b5%90-45%ed%9a%8c-%ec%a1%b8%ec%9e%91%ec%9e%91%ed%92%88-%ed%8c%a8%ec%85%98%ec%87%bc/","retrieved":1683697235518,"image":"https://d27rhg3fr98tz.cloudfront.net/wp-content/uploads/2023/05/10224453/%EC%98%A8%EB%9D%BC%EC%9D%B8-%ED%99%88%ED%8E%98%EC%9D%B4%EC%A7%80-%ED%8F%AC%EC%8A%A4%ED%84%B0-001-1-227x282.jpg"}]}