{"title":"노들섬 ─ 프로그램 ─ 현재 ─ 공연","url":"https://nodeul.org/program-present/#show","favicon":"https://s3-ap-northeast-2.amazonaws.com/nodeul-denomix/wp-content/themes/nodeul/img/favicons/favicon-32x32.png?v=190814","elements":[{"title":"PLANET – ALPHA 콘서트","contents":"2023.02.28 (화) 18:00","link":"https://nodeul.org/program/planet-alpha-%ec%bd%98%ec%84%9c%ed%8a%b8/","retrieved":1677519756352,"image":"https://d27rhg3fr98tz.cloudfront.net/wp-content/uploads/2023/02/15035737/thumb_600x900-227x282.jpg"}]}